optimodel/__init__.py
optimodel/envVars.py
optimodel/Consts/__init__.py
optimodel/ListModels/ListModels.py
optimodel/ListModels/__init__.py
optimodel/QueryModel/QueryModel.py
optimodel/QueryModel/__init__.py
optimodel/Utils/__init__.py
optimodel/Utils/HTTPClient/HTTPClient.py
optimodel/Utils/HTTPClient/__init__.py
optimodel_py-1.11.3.dist-info/METADATA
optimodel_py-1.11.3.dist-info/WHEEL
optimodel_py-1.11.3.dist-info/top_level.txt
optimodel_py-1.11.3.dist-info/RECORD
