Metadata-Version: 2.1
Name: optimodel-py
Version: 1.11.3
Summary: A smart framework for calling models in the most efficient way possible
Author-email: Lytix <support@lytix.com>
Project-URL: Homepage, https://github.com/Lytix-Labs/optimodel
Project-URL: Issues, https://github.com/Lytix-Labs/optimodel/issues
Classifier: Programming Language :: Python :: 3
Classifier: License :: OSI Approved :: MIT License
Classifier: Operating System :: OS Independent
Requires-Python: >=3.8
Requires-Dist: requests ==2.31.0
Requires-Dist: urllib3 ==2.2.1
Requires-Dist: aiohttp ==3.9.5
Requires-Dist: optimodel-server ==1.10.2
Requires-Dist: optimodel-types ==0.1.4
